DESCRIPTION.rst
MANIFEST.in
setup.py
WordBuilder.egg-info/PKG-INFO
WordBuilder.egg-info/SOURCES.txt
WordBuilder.egg-info/dependency_links.txt
WordBuilder.egg-info/top_level.txt
wordbuilder/WordBuilder.py
wordbuilder/__init__.py