Metadata-Version: 1.1
Name: WordBuilder
Version: 0.1.3
Summary: Creates new words based on an input corpus
Home-page: https://github.com/mouse-reeve/word-builder
Author: Mouse Reeve
Author-email: mouse.reeve@gmail.com
License: MIT
Keywords: generative language
Platform: UNKNOWN
Classifier: Development Status :: 3 - Alpha
Classifier: Intended Audience :: Developers
Classifier: Topic :: Artistic Software
Classifier: License :: OSI Approved :: MIT License
Classifier: Programming Language :: Python :: 2
Classifier: Programming Language :: Python :: 2.7
